MANIFEST.in
README.md
setup.cfg
setup.py
versioneer.py
src/kabaret/__init__.py
src/kabaret.kitsu.egg-info/PKG-INFO
src/kabaret.kitsu.egg-info/SOURCES.txt
src/kabaret.kitsu.egg-info/dependency_links.txt
src/kabaret.kitsu.egg-info/requires.txt
src/kabaret.kitsu.egg-info/top_level.txt
src/kabaret/kitsu/__init__.py
src/kabaret/kitsu/_version.py
src/kabaret/kitsu/flow/__init__.py
src/kabaret/kitsu/flow/kitsu.py
src/kabaret/kitsu/flow/maputils.py