Metadata-Version: 2.1
Name: kabaret.kitsu
Version: 0.0.0a1
Summary: Kitsu extension for the Kabaret framework
Home-page: https://gitlab.com/kabaretstudio/kabaret.kitsu
Author: Damien "dee" Coureau
Author-email: kabaret-dev@googlegroups.com
License: LGPLv3+
Keywords: kabaret cgwire kitsu gazu animation pipeline
Platform: UNKNOWN
Classifier: Development Status :: 2 - Pre-Alpha
Classifier: Intended Audience :: Developers
Classifier: License :: OSI Approved :: GNU Lesser General Public License v3 or later (LGPLv3+)
Requires-Python: >=2.7,!=3.0.*,!=3.1.*,!=3.2.*
Provides-Extra: dev
